[
    {
        "League":  "nhl",
        "GameId":  "9d0b725f6e813c43975b6ac5532309a6",
        "HomeTeam":  "New Jersey Devils",
        "AwayTeam":  "Buffalo Sabres",
        "HomeScore":  null,
        "AwayScore":  null,
        "Winner":  "Unknown",
        "Completed":  false,
        "Timestamp":  "2026-02-24 00:00:02"
    },
    {
        "League":  "nhl",
        "GameId":  "e8c18f2b16ac22ddc4b6160e03b48432",
        "HomeTeam":  "Washington Capitals",
        "AwayTeam":  "Philadelphia Flyers",
        "HomeScore":  null,
        "AwayScore":  null,
        "Winner":  "Unknown",
        "Completed":  false,
        "Timestamp":  "2026-02-24 00:00:02"
    },
    {
        "League":  "nhl",
        "GameId":  "7db784c85f5a8503aae0321813e62475",
        "HomeTeam":  "Tampa Bay Lightning",
        "AwayTeam":  "Toronto Maple Leafs",
        "HomeScore":  null,
        "AwayScore":  null,
        "Winner":  "Unknown",
        "Completed":  false,
        "Timestamp":  "2026-02-24 00:00:02"
    },
    {
        "League":  "nhl",
        "GameId":  "9e0efb6fbebb4688c447b7b8b9510376",
        "HomeTeam":  "Dallas Stars",
        "AwayTeam":  "Seattle Kraken",
        "HomeScore":  null,
        "AwayScore":  null,
        "Winner":  "Unknown",
        "Completed":  false,
        "Timestamp":  "2026-02-24 00:00:02"
    },
    {
        "League":  "nhl",
        "GameId":  "62d3d5c47cb28bbb3fe941b2a372da99",
        "HomeTeam":  "Utah Mammoth",
        "AwayTeam":  "Colorado Avalanche",
        "HomeScore":  null,
        "AwayScore":  null,
        "Winner":  "Unknown",
        "Completed":  false,
        "Timestamp":  "2026-02-24 00:00:02"
    },
    {
        "League":  "nhl",
        "GameId":  "ff44e0238a7b844ec02714e7e80fb7ae",
        "HomeTeam":  "Los Angeles Kings",
        "AwayTeam":  "Vegas Golden Knights",
        "HomeScore":  null,
        "AwayScore":  null,
        "Winner":  "Unknown",
        "Completed":  false,
        "Timestamp":  "2026-02-24 00:00:02"
    },
    {
        "League":  "nhl",
        "GameId":  "c7e030f8824a01e811126ffe9260e414",
        "HomeTeam":  "Vancouver Canucks",
        "AwayTeam":  "Winnipeg Jets",
        "HomeScore":  null,
        "AwayScore":  null,
        "Winner":  "Unknown",
        "Completed":  false,
        "Timestamp":  "2026-02-24 00:00:02"
    },
    {
        "League":  "nhl",
        "GameId":  "70ad639dbfb1b1f17f503857920380dd",
        "HomeTeam":  "Anaheim Ducks",
        "AwayTeam":  "Edmonton Oilers",
        "HomeScore":  null,
        "AwayScore":  null,
        "Winner":  "Unknown",
        "Completed":  false,
        "Timestamp":  "2026-02-24 00:00:02"
    },
    {
        "League":  "ncaab",
        "GameId":  "ba70c24dee6cdd4c257de854841d2b8a",
        "HomeTeam":  "New Haven Chargers",
        "AwayTeam":  "St. Francis (PA) Red Flash",
        "HomeScore":  null,
        "AwayScore":  null,
        "Winner":  "Unknown",
        "Completed":  false,
        "Timestamp":  "2026-02-24 00:00:05"
    },
    {
        "League":  "ncaab",
        "GameId":  "9d4f2750bb648b69807562735209f8ed",
        "HomeTeam":  "Eastern Michigan Eagles",
        "AwayTeam":  "Miami (OH) RedHawks",
        "HomeScore":  null,
        "AwayScore":  null,
        "Winner":  "Unknown",
        "Completed":  false,
        "Timestamp":  "2026-02-24 00:00:05"
    },
    {
        "League":  "ncaab",
        "GameId":  "30ad5a1b5fcdc6a19974dfa7c4189059",
        "HomeTeam":  "La Salle Explorers",
        "AwayTeam":  "GW Revolutionaries",
        "HomeScore":  null,
        "AwayScore":  null,
        "Winner":  "Unknown",
        "Completed":  false,
        "Timestamp":  "2026-02-24 00:00:05"
    },
    {
        "League":  "ncaab",
        "GameId":  "289bc0301e48270d57b2f612d5c33018",
        "HomeTeam":  "Rutgers Scarlet Knights",
        "AwayTeam":  "Washington Huskies",
        "HomeScore":  null,
        "AwayScore":  null,
        "Winner":  "Unknown",
        "Completed":  false,
        "Timestamp":  "2026-02-24 00:00:05"
    },
    {
        "League":  "ncaab",
        "GameId":  "de8b722d03702c260014bd949adfdf55",
        "HomeTeam":  "Akron Zips",
        "AwayTeam":  "Buffalo Bulls",
        "HomeScore":  null,
        "AwayScore":  null,
        "Winner":  "Unknown",
        "Completed":  false,
        "Timestamp":  "2026-02-24 00:00:05"
    },
    {
        "League":  "ncaab",
        "GameId":  "b95d3d252a019b7e317a80fdbd4d27d2",
        "HomeTeam":  "Ball State Cardinals",
        "AwayTeam":  "Massachusetts Minutemen",
        "HomeScore":  null,
        "AwayScore":  null,
        "Winner":  "Unknown",
        "Completed":  false,
        "Timestamp":  "2026-02-24 00:00:05"
    },
    {
        "League":  "ncaab",
        "GameId":  "4c3c17ba5c8366121892923e997ce944",
        "HomeTeam":  "Boston College Eagles",
        "AwayTeam":  "Wake Forest Demon Deacons",
        "HomeScore":  null,
        "AwayScore":  null,
        "Winner":  "Unknown",
        "Completed":  false,
        "Timestamp":  "2026-02-24 00:00:05"
    },
    {
        "League":  "ncaab",
        "GameId":  "d2645dfa80c8b68dc0a3e4a9b7c507e0",
        "HomeTeam":  "Bowling Green Falcons",
        "AwayTeam":  "Western Michigan Broncos",
        "HomeScore":  null,
        "AwayScore":  null,
        "Winner":  "Unknown",
        "Completed":  false,
        "Timestamp":  "2026-02-24 00:00:05"
    },
    {
        "League":  "ncaab",
        "GameId":  "43f070e0dcf2059c318be11b15ab36ce",
        "HomeTeam":  "Kent State Golden Flashes",
        "AwayTeam":  "Central Michigan Chippewas",
        "HomeScore":  null,
        "AwayScore":  null,
        "Winner":  "Unknown",
        "Completed":  false,
        "Timestamp":  "2026-02-24 00:00:05"
    },
    {
        "League":  "ncaab",
        "GameId":  "4fcca9b1254291807624ef68edf27d50",
        "HomeTeam":  "Texas Tech Red Raiders",
        "AwayTeam":  "Cincinnati Bearcats",
        "HomeScore":  null,
        "AwayScore":  null,
        "Winner":  "Unknown",
        "Completed":  false,
        "Timestamp":  "2026-02-24 00:00:05"
    },
    {
        "League":  "ncaab",
        "GameId":  "3e519f09608b7918502d97faabc033a7",
        "HomeTeam":  "Dayton Flyers",
        "AwayTeam":  "Saint Louis Billikens",
        "HomeScore":  null,
        "AwayScore":  null,
        "Winner":  "Unknown",
        "Completed":  false,
        "Timestamp":  "2026-02-24 00:00:05"
    },
    {
        "League":  "ncaab",
        "GameId":  "db808f0b65980aebcae3a480d1bf59ec",
        "HomeTeam":  "Notre Dame Fighting Irish",
        "AwayTeam":  "Duke Blue Devils",
        "HomeScore":  null,
        "AwayScore":  null,
        "Winner":  "Unknown",
        "Completed":  false,
        "Timestamp":  "2026-02-24 00:00:05"
    },
    {
        "League":  "ncaab",
        "GameId":  "21e7fc1da391c5a6da12aa9ecc2c2067",
        "HomeTeam":  "Georgetown Hoyas",
        "AwayTeam":  "Marquette Golden Eagles",
        "HomeScore":  null,
        "AwayScore":  null,
        "Winner":  "Unknown",
        "Completed":  false,
        "Timestamp":  "2026-02-24 00:00:05"
    },
    {
        "League":  "ncaab",
        "GameId":  "8c8519e90b6d829aae3167011d5ff34e",
        "HomeTeam":  "Indiana Hoosiers",
        "AwayTeam":  "Northwestern Wildcats",
        "HomeScore":  null,
        "AwayScore":  null,
        "Winner":  "Unknown",
        "Completed":  false,
        "Timestamp":  "2026-02-24 00:00:05"
    },
    {
        "League":  "ncaab",
        "GameId":  "b7a8be4db06bc529819c4fee2c759d8f",
        "HomeTeam":  "Troy Trojans",
        "AwayTeam":  "Louisiana Ragin\u0027 Cajuns",
        "HomeScore":  null,
        "AwayScore":  null,
        "Winner":  "Unknown",
        "Completed":  false,
        "Timestamp":  "2026-02-24 00:00:05"
    },
    {
        "League":  "ncaab",
        "GameId":  "e1a7f538661b850dd0411f865499d745",
        "HomeTeam":  "Marshall Thundering Herd",
        "AwayTeam":  "Old Dominion Monarchs",
        "HomeScore":  null,
        "AwayScore":  null,
        "Winner":  "Unknown",
        "Completed":  false,
        "Timestamp":  "2026-02-24 00:00:05"
    },
    {
        "League":  "ncaab",
        "GameId":  "54683b79bb4d36eb07057ce5cf01dc67",
        "HomeTeam":  "Toledo Rockets",
        "AwayTeam":  "Northern Illinois Huskies",
        "HomeScore":  null,
        "AwayScore":  null,
        "Winner":  "Unknown",
        "Completed":  false,
        "Timestamp":  "2026-02-24 00:00:05"
    },
    {
        "League":  "ncaab",
        "GameId":  "2e30669ce7e67ce86aebc8cacfe15178",
        "HomeTeam":  "Oklahoma St Cowboys",
        "AwayTeam":  "West Virginia Mountaineers",
        "HomeScore":  null,
        "AwayScore":  null,
        "Winner":  "Unknown",
        "Completed":  false,
        "Timestamp":  "2026-02-24 00:00:05"
    },
    {
        "League":  "ncaab",
        "GameId":  "6c195451fcf40da48f04be88bb38753a",
        "HomeTeam":  "South Carolina Gamecocks",
        "AwayTeam":  "Kentucky Wildcats",
        "HomeScore":  null,
        "AwayScore":  null,
        "Winner":  "Unknown",
        "Completed":  false,
        "Timestamp":  "2026-02-24 00:00:05"
    },
    {
        "League":  "ncaab",
        "GameId":  "ab2376e5b605176205f9c2440ecaee64",
        "HomeTeam":  "Virginia Cavaliers",
        "AwayTeam":  "NC State Wolfpack",
        "HomeScore":  null,
        "AwayScore":  null,
        "Winner":  "Unknown",
        "Completed":  false,
        "Timestamp":  "2026-02-24 00:00:05"
    },
    {
        "League":  "ncaab",
        "GameId":  "ea0fec305204313e184095baf807fd6c",
        "HomeTeam":  "Georgia St Panthers",
        "AwayTeam":  "Coastal Carolina Chanticleers",
        "HomeScore":  null,
        "AwayScore":  null,
        "Winner":  "Unknown",
        "Completed":  false,
        "Timestamp":  "2026-02-24 00:00:05"
    },
    {
        "League":  "ncaab",
        "GameId":  "11678980c7822d3650fe45385c589b0e",
        "HomeTeam":  "Morehead St Eagles",
        "AwayTeam":  "Southern Indiana Screaming Eagles",
        "HomeScore":  null,
        "AwayScore":  null,
        "Winner":  "Unknown",
        "Completed":  false,
        "Timestamp":  "2026-02-24 00:00:05"
    },
    {
        "League":  "ncaab",
        "GameId":  "f1652afbd1f33c0f460e3ee973c38400",
        "HomeTeam":  "Providence Friars",
        "AwayTeam":  "Xavier Musketeers",
        "HomeScore":  null,
        "AwayScore":  null,
        "Winner":  "Unknown",
        "Completed":  false,
        "Timestamp":  "2026-02-24 00:00:05"
    },
    {
        "League":  "ncaab",
        "GameId":  "356dde1b2d8c487e49f3bd174152dd88",
        "HomeTeam":  "UIC Flames",
        "AwayTeam":  "Bradley Braves",
        "HomeScore":  null,
        "AwayScore":  null,
        "Winner":  "Unknown",
        "Completed":  false,
        "Timestamp":  "2026-02-24 00:00:05"
    },
    {
        "League":  "ncaab",
        "GameId":  "b0b05591f4e8d3972867b90316e68d50",
        "HomeTeam":  "Arkansas St Red Wolves",
        "AwayTeam":  "Southern Miss Golden Eagles",
        "HomeScore":  null,
        "AwayScore":  null,
        "Winner":  "Unknown",
        "Completed":  false,
        "Timestamp":  "2026-02-24 00:00:05"
    },
    {
        "League":  "ncaab",
        "GameId":  "643f5e2124604992f05bab8202bab4be",
        "HomeTeam":  "Michigan Wolverines",
        "AwayTeam":  "Minnesota Golden Gophers",
        "HomeScore":  null,
        "AwayScore":  null,
        "Winner":  "Unknown",
        "Completed":  false,
        "Timestamp":  "2026-02-24 00:00:05"
    },
    {
        "League":  "ncaab",
        "GameId":  "f01d666fdd942a80573a9412bbff08d9",
        "HomeTeam":  "Air Force Falcons",
        "AwayTeam":  "San José St Spartans",
        "HomeScore":  null,
        "AwayScore":  null,
        "Winner":  "Unknown",
        "Completed":  false,
        "Timestamp":  "2026-02-24 00:00:05"
    },
    {
        "League":  "ncaab",
        "GameId":  "98558fdb0980a6262a34e1145f8e0180",
        "HomeTeam":  "TCU Horned Frogs",
        "AwayTeam":  "Arizona St Sun Devils",
        "HomeScore":  null,
        "AwayScore":  null,
        "Winner":  "Unknown",
        "Completed":  false,
        "Timestamp":  "2026-02-24 00:00:05"
    },
    {
        "League":  "ncaab",
        "GameId":  "d2f8992d40ce887fa0fa7629ac239a3d",
        "HomeTeam":  "Baylor Bears",
        "AwayTeam":  "Arizona Wildcats",
        "HomeScore":  null,
        "AwayScore":  null,
        "Winner":  "Unknown",
        "Completed":  false,
        "Timestamp":  "2026-02-24 00:00:05"
    },
    {
        "League":  "ncaab",
        "GameId":  "2dacfe177d0fc6ad8a6976693b046ace",
        "HomeTeam":  "Oklahoma Sooners",
        "AwayTeam":  "Auburn Tigers",
        "HomeScore":  null,
        "AwayScore":  null,
        "Winner":  "Unknown",
        "Completed":  false,
        "Timestamp":  "2026-02-24 00:00:05"
    },
    {
        "League":  "ncaab",
        "GameId":  "731927dad07beae344676e64d69c75c3",
        "HomeTeam":  "Boise State Broncos",
        "AwayTeam":  "Wyoming Cowboys",
        "HomeScore":  null,
        "AwayScore":  null,
        "Winner":  "Unknown",
        "Completed":  false,
        "Timestamp":  "2026-02-24 00:00:05"
    },
    {
        "League":  "ncaab",
        "GameId":  "375be27fbbe10a43f6be6d99b74e9d68",
        "HomeTeam":  "Colorado St Rams",
        "AwayTeam":  "Fresno St Bulldogs",
        "HomeScore":  null,
        "AwayScore":  null,
        "Winner":  "Unknown",
        "Completed":  false,
        "Timestamp":  "2026-02-24 00:00:05"
    },
    {
        "League":  "ncaab",
        "GameId":  "2a591f71538432bdbcd9777ee231240a",
        "HomeTeam":  "Florida St Seminoles",
        "AwayTeam":  "Miami Hurricanes",
        "HomeScore":  null,
        "AwayScore":  null,
        "Winner":  "Unknown",
        "Completed":  false,
        "Timestamp":  "2026-02-24 00:00:05"
    },
    {
        "League":  "ncaab",
        "GameId":  "a28a4e07525f14a6930fa8fe46b0d9a9",
        "HomeTeam":  "Utah Utes",
        "AwayTeam":  "Iowa State Cyclones",
        "HomeScore":  null,
        "AwayScore":  null,
        "Winner":  "Unknown",
        "Completed":  false,
        "Timestamp":  "2026-02-24 00:00:05"
    },
    {
        "League":  "ncaab",
        "GameId":  "206b5edc5d33a6553ca14f1b21a3b282",
        "HomeTeam":  "Missouri Tigers",
        "AwayTeam":  "Tennessee Volunteers",
        "HomeScore":  null,
        "AwayScore":  null,
        "Winner":  "Unknown",
        "Completed":  false,
        "Timestamp":  "2026-02-24 00:00:05"
    },
    {
        "League":  "ncaab",
        "GameId":  "62966c4168ed6fc251a707fcd7971601",
        "HomeTeam":  "BYU Cougars",
        "AwayTeam":  "UCF Knights",
        "HomeScore":  null,
        "AwayScore":  null,
        "Winner":  "Unknown",
        "Completed":  false,
        "Timestamp":  "2026-02-24 00:00:05"
    },
    {
        "League":  "ncaab",
        "GameId":  "ad340d3cad6aee5133a020efd286a14b",
        "HomeTeam":  "Nevada Wolf Pack",
        "AwayTeam":  "New Mexico Lobos",
        "HomeScore":  null,
        "AwayScore":  null,
        "Winner":  "Unknown",
        "Completed":  false,
        "Timestamp":  "2026-02-24 00:00:05"
    },
    {
        "League":  "ncaab",
        "GameId":  "37a2a5e99a1257971b8852db16a1d900",
        "HomeTeam":  "UCLA Bruins",
        "AwayTeam":  "USC Trojans",
        "HomeScore":  null,
        "AwayScore":  null,
        "Winner":  "Unknown",
        "Completed":  false,
        "Timestamp":  "2026-02-24 00:00:05"
    },
    {
        "League":  "nba",
        "GameId":  "56d8ed44cdc3ee05a77edd2ecb4a516b",
        "HomeTeam":  "Indiana Pacers",
        "AwayTeam":  "Philadelphia 76ers",
        "HomeScore":  null,
        "AwayScore":  null,
        "Winner":  "Unknown",
        "Completed":  false,
        "Timestamp":  "2026-02-24 00:00:06"
    },
    {
        "League":  "nba",
        "GameId":  "9b47a98c27ee6ad7706c0e3a34887d12",
        "HomeTeam":  "Atlanta Hawks",
        "AwayTeam":  "Washington Wizards",
        "HomeScore":  null,
        "AwayScore":  null,
        "Winner":  "Unknown",
        "Completed":  false,
        "Timestamp":  "2026-02-24 00:00:06"
    },
    {
        "League":  "nba",
        "GameId":  "ba1cbfef82b196c39c27c0a78d2f22f4",
        "HomeTeam":  "Brooklyn Nets",
        "AwayTeam":  "Dallas Mavericks",
        "HomeScore":  null,
        "AwayScore":  null,
        "Winner":  "Unknown",
        "Completed":  false,
        "Timestamp":  "2026-02-24 00:00:06"
    },
    {
        "League":  "nba",
        "GameId":  "9309db11d70c5cca506e8df2ce5e1fb3",
        "HomeTeam":  "Toronto Raptors",
        "AwayTeam":  "Oklahoma City Thunder",
        "HomeScore":  null,
        "AwayScore":  null,
        "Winner":  "Unknown",
        "Completed":  false,
        "Timestamp":  "2026-02-24 00:00:06"
    },
    {
        "League":  "nba",
        "GameId":  "afa313a4ac57c385b346c4d1b4912e3c",
        "HomeTeam":  "Chicago Bulls",
        "AwayTeam":  "Charlotte Hornets",
        "HomeScore":  null,
        "AwayScore":  null,
        "Winner":  "Unknown",
        "Completed":  false,
        "Timestamp":  "2026-02-24 00:00:06"
    },
    {
        "League":  "nba",
        "GameId":  "a4f9fe2c493fda08ff19d7c349948824",
        "HomeTeam":  "Cleveland Cavaliers",
        "AwayTeam":  "New York Knicks",
        "HomeScore":  null,
        "AwayScore":  null,
        "Winner":  "Unknown",
        "Completed":  false,
        "Timestamp":  "2026-02-24 00:00:06"
    },
    {
        "League":  "nba",
        "GameId":  "eeaef64ecae77969994ee0b8b56da256",
        "HomeTeam":  "New Orleans Pelicans",
        "AwayTeam":  "Golden State Warriors",
        "HomeScore":  null,
        "AwayScore":  null,
        "Winner":  "Unknown",
        "Completed":  false,
        "Timestamp":  "2026-02-24 00:00:06"
    },
    {
        "League":  "nba",
        "GameId":  "d8b8e015e358036b0f8e3758c263ae24",
        "HomeTeam":  "Milwaukee Bucks",
        "AwayTeam":  "Miami Heat",
        "HomeScore":  null,
        "AwayScore":  null,
        "Winner":  "Unknown",
        "Completed":  false,
        "Timestamp":  "2026-02-24 00:00:06"
    },
    {
        "League":  "nba",
        "GameId":  "0bd210b80d8411885dccc7164a922234",
        "HomeTeam":  "Phoenix Suns",
        "AwayTeam":  "Boston Celtics",
        "HomeScore":  null,
        "AwayScore":  null,
        "Winner":  "Unknown",
        "Completed":  false,
        "Timestamp":  "2026-02-24 00:00:06"
    },
    {
        "League":  "nba",
        "GameId":  "f1b2d64d6f68c92256c27ebe3868b62a",
        "HomeTeam":  "Portland Trail Blazers",
        "AwayTeam":  "Minnesota Timberwolves",
        "HomeScore":  null,
        "AwayScore":  null,
        "Winner":  "Unknown",
        "Completed":  false,
        "Timestamp":  "2026-02-24 00:00:06"
    },
    {
        "League":  "nba",
        "GameId":  "19016c4fd819260622e9fbaf8070d66a",
        "HomeTeam":  "Los Angeles Lakers",
        "AwayTeam":  "Orlando Magic",
        "HomeScore":  null,
        "AwayScore":  null,
        "Winner":  "Unknown",
        "Completed":  false,
        "Timestamp":  "2026-02-24 00:00:06"
    },
    {
        "League":  "ncaaf",
        "GameId":  "123a238486098cc9e8f71fea0cf4e7b0",
        "HomeTeam":  "Virginia Cavaliers",
        "AwayTeam":  "NC State Wolfpack",
        "HomeScore":  null,
        "AwayScore":  null,
        "Winner":  "Unknown",
        "Completed":  false,
        "Timestamp":  "2026-02-24 00:00:07"
    },
    {
        "League":  "ncaaf",
        "GameId":  "2c288580da16e12d35355f2548721be6",
        "HomeTeam":  "TCU Horned Frogs",
        "AwayTeam":  "North Carolina Tar Heels",
        "HomeScore":  null,
        "AwayScore":  null,
        "Winner":  "Unknown",
        "Completed":  false,
        "Timestamp":  "2026-02-24 00:00:07"
    },
    {
        "League":  "ncaaf",
        "GameId":  "525909f6be5e505d076a97eb097528eb",
        "HomeTeam":  "Auburn Tigers",
        "AwayTeam":  "Baylor Bears",
        "HomeScore":  null,
        "AwayScore":  null,
        "Winner":  "Unknown",
        "Completed":  false,
        "Timestamp":  "2026-02-24 00:00:07"
    },
    {
        "League":  "ncaaf",
        "GameId":  "1bb9e45b6e7ed1200104ed018eff9093",
        "HomeTeam":  "California Golden Bears",
        "AwayTeam":  "UCLA Bruins",
        "HomeScore":  null,
        "AwayScore":  null,
        "Winner":  "Unknown",
        "Completed":  false,
        "Timestamp":  "2026-02-24 00:00:07"
    },
    {
        "League":  "ncaaf",
        "GameId":  "073bba47dc105fcd66913e74f281ae96",
        "HomeTeam":  "LSU Tigers",
        "AwayTeam":  "Clemson Tigers",
        "HomeScore":  null,
        "AwayScore":  null,
        "Winner":  "Unknown",
        "Completed":  false,
        "Timestamp":  "2026-02-24 00:00:07"
    },
    {
        "League":  "ncaaf",
        "GameId":  "b460f3aa4235ec2485f25182755304d6",
        "HomeTeam":  "Notre Dame Fighting Irish",
        "AwayTeam":  "Wisconsin Badgers",
        "HomeScore":  null,
        "AwayScore":  null,
        "Winner":  "Unknown",
        "Completed":  false,
        "Timestamp":  "2026-02-24 00:00:07"
    },
    {
        "League":  "ncaaf",
        "GameId":  "b38f4f63351c15767e64a76a73589574",
        "HomeTeam":  "Michigan Wolverines",
        "AwayTeam":  "Oklahoma Sooners",
        "HomeScore":  null,
        "AwayScore":  null,
        "Winner":  "Unknown",
        "Completed":  false,
        "Timestamp":  "2026-02-24 00:00:07"
    },
    {
        "League":  "ncaaf",
        "GameId":  "08c34029ecc85b4a6d519f90f9082e56",
        "HomeTeam":  "Texas Longhorns",
        "AwayTeam":  "Ohio State Buckeyes",
        "HomeScore":  null,
        "AwayScore":  null,
        "Winner":  "Unknown",
        "Completed":  false,
        "Timestamp":  "2026-02-24 00:00:07"
    }
]
